gpyrn/__init__.py
gpyrn/_gp.py
gpyrn/_plots.py
gpyrn/_utils.py
gpyrn/covfunc.py
gpyrn/evidence.py
gpyrn/meanfield.py
gpyrn/meanfunc.py
gpyrn/nonparametric.py
gpyrn-1.0.1.dist-info/LICENSE
gpyrn-1.0.1.dist-info/METADATA
gpyrn-1.0.1.dist-info/WHEEL
gpyrn-1.0.1.dist-info/top_level.txt
gpyrn-1.0.1.dist-info/RECORD
