Metadata-Version: 2.1
Name: gpyrn
Version: 1.0.1
Summary: Gaussian process regression networks for exoplanet detection
Home-page: https://github.com/iastro-pt/gpyrn
Author: João Camacho
Author-email: joao.camacho@astro.up.pt
License: MIT
License-File: LICENSE
